smarterbombing/__init__.py
smarterbombing/__main__.py
smarterbombing/aggregrator/__init__.py
smarterbombing/aggregrator/aggregator.py
smarterbombing/aggregrator/damage_graph_aggregator.py
smarterbombing/aggregrator/site_statistics_aggregator.py
smarterbombing/app/squad.py
smarterbombing/configuration.py
smarterbombing/logs/__init__.py
smarterbombing/logs/log_locator.py
smarterbombing/logs/log_reader.py
smarterbombing/parsing/__init__.py
smarterbombing/parsing/combat_log_parser.py
smarterbombing/webui/__init__.py
smarterbombing/webui/html_generate_statistics.py
smarterbombing/webui/ui.py
smarterbombing/webui/ui_squad.py
smarterbombing/webui/ui_squads.py
smarterbombing-0.5.1.dist-info/LICENSE
smarterbombing-0.5.1.dist-info/METADATA
smarterbombing-0.5.1.dist-info/WHEEL
smarterbombing-0.5.1.dist-info/RECORD
