Metadata-Version: 2.1
Name: smarterbombing
Version: 0.5.1
Summary: A tool which reads combat logs from Eve Online and displays statistics.
Home-page: https://github.com/agelito/eve-smarterbombing
License: MIT
Author: Axel Wettervik
Author-email: axel.wettervik@gmail.com
Requires-Python: >=3.8,<4.0
Classifier: License :: OSI Approved :: MIT License
Classifier: Programming Language :: Python :: 3
Classifier: Programming Language :: Python :: 3.8
Classifier: Programming Language :: Python :: 3.9
Classifier: Programming Language :: Python :: 3.10
Classifier: Programming Language :: Python :: 3.11
Requires-Dist: gradio (>=3.33.1,<4.0.0)
Requires-Dist: matplotlib (>=3.7.1,<4.0.0)
Requires-Dist: pandas (>=2.0.2,<3.0.0)
Requires-Dist: pyyaml (>=6.0,<7.0)
Requires-Dist: tabulate (>=0.9.0,<0.10.0)
Project-URL: Repository, https://github.com/agelito/eve-smarterbombing
